nisardev/__init__.py
nisardev/cvPoints.py
nisardev/nisarBase2D.py
nisardev/nisarImage.py
nisardev/nisarImageSeries.py
nisardev/nisarSupport.py
nisardev/nisarVel.py
nisardev/nisarVelSeries.py
nisardev-0.0.9.dist-info/LICENSE
nisardev-0.0.9.dist-info/METADATA
nisardev-0.0.9.dist-info/WHEEL
nisardev-0.0.9.dist-info/RECORD
